LICENSE
MANIFEST.in
README.md
setup.py
dettectinator/__init__.py
dettectinator/attack_taxii_client.py
dettectinator/cli.py
dettectinator/constants.py
dettectinator/dettectinator.py
dettectinator/testdettectinator.py
dettectinator.egg-info/PKG-INFO
dettectinator.egg-info/SOURCES.txt
dettectinator.egg-info/dependency_links.txt
dettectinator.egg-info/requires.txt
dettectinator.egg-info/top_level.txt
dettectinator/plugins/__init__.py
dettectinator/plugins/datasources_import.py
dettectinator/plugins/groups_import.py
dettectinator/plugins/technique_import.py
dettectinator/plugins/support/__init__.py
dettectinator/plugins/support/authentication.py
dettectinator/plugins/support/msal_patch.py