Metadata-Version: 2.1
Name: dettectinator
Version: 1.4.3
Summary: Dettectinator - The Python library to your DeTT&CT YAML files.
Home-page: https://github.com/siriussecurity/dettectinator
Author: Sirius Security
License: GPL3
Project-URL: Documentation, https://github.com/siriussecurity/dettectinator/wiki
Project-URL: Code, https://github.com/siriussecurity/dettectinator
Project-URL: Issue tracker, https://github.com/siriussecurity/dettectinator/issues
Keywords: mitre attack dettect soc threat hunting
Classifier: Development Status :: 5 - Production/Stable
Classifier: Operating System :: OS Independent
Classifier: Topic :: Security
Classifier: License :: OSI Approved :: GNU General Public License v3 (GPLv3)
Classifier: Programming Language :: Python :: 3.9
License-File: LICENSE
Requires-Dist: requests
Requires-Dist: ruamel.yaml
Requires-Dist: python-dateutil
Requires-Dist: msal
Requires-Dist: stix2
Requires-Dist: openpyxl
Requires-Dist: suricataparser
Requires-Dist: addonfactory-splunk-conf-parser-lib
Requires-Dist: pandas
Requires-Dist: anyascii
Requires-Dist: pypdf
